DESCRIPTION.rst
MANIFEST.in
sar.py
setup.py
sar_tool.egg-info/PKG-INFO
sar_tool.egg-info/SOURCES.txt
sar_tool.egg-info/dependency_links.txt
sar_tool.egg-info/entry_points.txt
sar_tool.egg-info/top_level.txt