Metadata-Version: 1.1
Name: sar-tool
Version: 1.0.3
Summary: Search and replace tool that outputs a diff compatible with patch
Home-page: https://github.com/naufraghi/sar
Author: Matteo Bertini
Author-email: matteo@naufraghi.net
License: MIT
Keywords: sed grep awk diff patch
Platform: UNKNOWN
Classifier: Development Status :: 5 - Production/Stable
Classifier: Intended Audience :: System Administrators
Classifier: Intended Audience :: Developers
Classifier: Environment :: Console
Classifier: License :: OSI Approved :: MIT License
Classifier: Programming Language :: Python :: 2
Classifier: Programming Language :: Python :: 2.7
Classifier: Programming Language :: Python :: 3
Classifier: Topic :: System :: Systems Administration
Classifier: Topic :: Text Processing :: General
Classifier: Topic :: Utilities
